webllama/__init__.py
webllama/version.py
webllama/experimental/__init__.py
webllama/experimental/classes.py
webllama/experimental/formatting.py
webllama/experimental/functions.py
webllama/experimental/processing.py
webllama/experimental/integrations/__init__.py
webllama/experimental/integrations/browsergym/__init__.py
webllama/experimental/integrations/browsergym/functions.py
webllama/experimental/templates/__init__.py
webllama/experimental/templates/weblinx.py
webllama/experimental/web/__init__.py
webllama/experimental/web/client.py
webllama/experimental/web/server.py
webllama-0.1.0.dist-info/LICENSE
webllama-0.1.0.dist-info/METADATA
webllama-0.1.0.dist-info/WHEEL
webllama-0.1.0.dist-info/top_level.txt
webllama-0.1.0.dist-info/RECORD
