Metadata-Version: 2.1
Name: webllama
Version: 0.1.0
Summary: Llama-powered agents for automatic web browsing
Home-page: https://github.com/McGill-NLP/webllama
Author: Xing Han Lù
Author-email: webllama@googlegroups.com
Classifier: Programming Language :: Python :: 3
Classifier: License :: OSI Approved :: MIT License
Classifier: Operating System :: OS Independent
Requires-Python: >=3.8
License-File: LICENSE
Requires-Dist: weblinx >=0.3.0rc1
Requires-Dist: lxml
Requires-Dist: numpy
Provides-Extra: all
Requires-Dist: black ; extra == 'all'
Requires-Dist: weblinx[eval] >=0.3.0.rc1 ; extra == 'all'
Requires-Dist: streamlit ; extra == 'all'
Requires-Dist: sentence-transformers ; extra == 'all'
Requires-Dist: transformers ; extra == 'all'
Requires-Dist: playwright ; extra == 'all'
Requires-Dist: browsergym ; extra == 'all'
Provides-Extra: dev
Requires-Dist: black ; extra == 'dev'
Provides-Extra: extra
Requires-Dist: weblinx[eval] >=0.3.0.rc1 ; extra == 'extra'
Requires-Dist: streamlit ; extra == 'extra'
Requires-Dist: sentence-transformers ; extra == 'extra'
Requires-Dist: transformers ; extra == 'extra'
Requires-Dist: playwright ; extra == 'extra'
Requires-Dist: browsergym ; extra == 'extra'
